setup.py
prob_dists/Binomialdistribution.py
prob_dists/Gaussiandistribution.py
prob_dists/Generaldistribution.py
prob_dists/__init__.py
prob_dists.egg-info/PKG-INFO
prob_dists.egg-info/SOURCES.txt
prob_dists.egg-info/dependency_links.txt
prob_dists.egg-info/not-zip-safe
prob_dists.egg-info/top_level.txt