Metadata-Version: 1.0
Name: prob-dists
Version: 0.1
Summary: Gaussian distributions
Home-page: UNKNOWN
Author: Malladi,Yeswanth chowdary
Author-email: malladi.yaswanth@gmail.com
License: UNKNOWN
Platform: UNKNOWN
